mlops_bydesign_quickstart/__init__.py
mlops_bydesign_quickstart/core.py
mlops_bydesign_quickstart-0.1.2.dist-info/licenses/LICENSE
mlops_bydesign_quickstart-0.1.2.dist-info/METADATA
mlops_bydesign_quickstart-0.1.2.dist-info/WHEEL
mlops_bydesign_quickstart-0.1.2.dist-info/top_level.txt
mlops_bydesign_quickstart-0.1.2.dist-info/RECORD
