Metadata-Version: 2.4
Name: mlops-bydesign-quickstart
Version: 0.1.2
Summary: Quickly create ML experiments with standardized folder 
Home-page: https://github.com/abelunbound/mlops-bydesign-quickstart
Author: Abel
License: MIT
Project-URL: Homepage, https://github.com/abelunbound/mlops-bydesign-quickstart
Project-URL: Repository, https://github.com/abelunbound/mlops-bydesign-quickstart
Requires-Python: >=3.8
License-File: LICENSE
Requires-Dist: PyYAML>=6.0
Dynamic: home-page
Dynamic: license-file
Dynamic: requires-python
